wormtrackatron7000/__init__.py
wormtrackatron7000/gui.py
wormtrackatron7000/main.py
wormtrackatron7000/plot_utils.py
wormtrackatron7000/worm_tracker.py
wormtrackatron7000/worm_tracker_utils.py
wormtrackatron7000-0.2.0.dist-info/METADATA
wormtrackatron7000-0.2.0.dist-info/WHEEL
wormtrackatron7000-0.2.0.dist-info/entry_points.txt
wormtrackatron7000-0.2.0.dist-info/licenses/LICENSE
wormtrackatron7000-0.2.0.dist-info/RECORD
