Metadata-Version: 2.4
Name: WORMTRACKATRON7000
Version: 0.2.0
Summary: A tool for tracking worm positions on plates with food patches.
Author-email: Stefan Rogers-Coltman <srogers@mrc-lmb.cam.ac.uk>
License-File: LICENSE
Classifier: License :: OSI Approved :: MIT License
Classifier: Operating System :: OS Independent
Classifier: Programming Language :: Python :: 3
Requires-Python: >=3.10
Requires-Dist: matplotlib>=3.4.0
Requires-Dist: opencv-python==4.10.0.84
Requires-Dist: pandas==2.2.3
Requires-Dist: pyqt6==6.8.0
